intro.py
marsbuggy-0.0.1.dist-info/DESCRIPTION.rst
marsbuggy-0.0.1.dist-info/METADATA
marsbuggy-0.0.1.dist-info/RECORD
marsbuggy-0.0.1.dist-info/WHEEL
marsbuggy-0.0.1.dist-info/metadata.json
marsbuggy-0.0.1.dist-info/top_level.txt
